{
    "prefix": ".",
    "quiet_prefix": ",",
    "sudo_prefix": "#",
    "languages": [
        "ita",
        "eng"
    ],
    "modules_status": {
        "message_reply": {
            "enabled": 1,
            "mode": 1
        },
        "bestemmia_reply": {
            "enabled": 1,
            "mode": 1
        },
        "badass_character_call": {
            "enabled": 1,
            "mode": 1
        },
        "pickup_line_call": {
            "enabled": 1,
            "mode": 1
        },
        "user_data_log": {
            "enabled": 1,
            "mode": 1
        },
        "mydata": {
            "enabled": 1,
            "mode": 1
        }
    }
}